casbin_rabbitmq_watcher/__init__.py
casbin_rabbitmq_watcher/watcher.py
casbin_rabbitmq_watcher-1.7.0.dist-info/licenses/LICENSE
tests/__init__.py
tests/test_rabbit_watcher.py
casbin_rabbitmq_watcher-1.7.0.dist-info/METADATA
casbin_rabbitmq_watcher-1.7.0.dist-info/WHEEL
casbin_rabbitmq_watcher-1.7.0.dist-info/top_level.txt
casbin_rabbitmq_watcher-1.7.0.dist-info/RECORD
