Metadata-Version: 2.4
Name: casbin-rabbitmq-watcher
Version: 1.7.0
Summary: Casbin role watcher to be used for monitoring updates to policies for PyCasbin
Home-page: https://github.com/officialpycasbin/rabbitmq-watcher
Author: Casbin
Author-email: admin@casbin.org
License: Apache 2.0
Keywords: pycasbin,casbin,Rabbitmq,casbin-watcher,rbac,access control,abac,acl,permission
Classifier: Programming Language :: Python :: 3.9
Classifier: Programming Language :: Python :: 3.10
Classifier: Programming Language :: Python :: 3.11
Classifier: Programming Language :: Python :: 3.12
Classifier: License :: OSI Approved :: Apache Software License
Classifier: Operating System :: OS Independent
Requires-Python: >=3.5
License-File: LICENSE
Requires-Dist: pycasbin>=2.0.0
Requires-Dist: pika>=1.3.0
Dynamic: author
Dynamic: author-email
Dynamic: classifier
Dynamic: description
Dynamic: description-content-type
Dynamic: home-page
Dynamic: keywords
Dynamic: license
Dynamic: license-file
Dynamic: requires-dist
Dynamic: requires-python
Dynamic: summary
